alkivi/__init__.py
alkivi/odoo/__init__.py
alkivi/odoo/client.py
alkivi/odoo/config.py
alkivi_odoo_client-1.0.3.dist-info/DESCRIPTION.rst
alkivi_odoo_client-1.0.3.dist-info/METADATA
alkivi_odoo_client-1.0.3.dist-info/RECORD
alkivi_odoo_client-1.0.3.dist-info/WHEEL
alkivi_odoo_client-1.0.3.dist-info/metadata.json
alkivi_odoo_client-1.0.3.dist-info/top_level.txt
